lcr/__init__.py
lcr_api-0.4.0.dist-info/METADATA
lcr_api-0.4.0.dist-info/WHEEL
lcr_api-0.4.0.dist-info/top_level.txt
lcr_api-0.4.0.dist-info/RECORD
