Metadata-Version: 2.1
Name: lcr-api
Version: 0.4.0
Summary: An API for The Church of Jesus Christ of Latter-day Saint's Leader and Clerk Resources (LCR)
Home-page: https://github.com/philipbl/LCR-API
Author: Philip Lundrigan
Author-email: philiplundrigan@gmail.com
License: MIT License
Download-URL: https://github.com/philipbl/LCR-API/archive/v0.4.0.zip
Platform: any
Requires-Dist: requests (<3,>=2)
